smurff/smurff.py
smurff/wrapper.cpp
smurff/_version.py
smurff/generate.py
smurff/center.py
smurff/cmdline.py
smurff/predict.py
smurff/datasets.py
smurff/wrapper.cpython-39-darwin.so
smurff/__init__.py
smurff/result.py
smurff/.gitignore
smurff/helper.py
smurff/trainsession.py
smurff/prepare.py
smurff/matrix_io.py
smurff-1.0.dist-info/RECORD
smurff-1.0.dist-info/WHEEL
smurff-1.0.dist-info/entry_points.txt
smurff-1.0.dist-info/METADATA
smurff-1.0.dist-info/licenses/LICENSE
