Metadata-Version: 2.2
Name: smurff
Version: 1.0
Summary: Bayesian Factorization Methods
Keywords: bayesian factorization machine-learning high-dimensional side-information
Author-Email: Tom Vander Aa <Tom.VanderAa@imec.be>
License: MIT
Classifier: Development Status :: 4 - Beta
Classifier: Intended Audience :: Science/Research
Classifier: License :: OSI Approved :: MIT License
Classifier: Operating System :: MacOS
Classifier: Operating System :: Microsoft :: Windows
Classifier: Operating System :: POSIX
Classifier: Operating System :: Unix
Classifier: Programming Language :: C++
Classifier: Programming Language :: Python
Classifier: Programming Language :: Python :: 3
Classifier: Topic :: Scientific/Engineering :: Artificial Intelligence
Project-URL: Homepage, http://github.com/ExaScience/smurff
Requires-Dist: h5sparse-tensor
Requires-Dist: numpy
Requires-Dist: pandas
Requires-Dist: scikit-learn
Requires-Dist: scipy
